[{
        "collectionName": "The Frey's",
        "tokenName": "The Frey",
        "image": "https://frey.freyala.com/images/3820.png",
        "status": "OPEN",
        "token": "0x3c8a8a7b7d0fea5078fb37c69e42b85d8fc6a063",
        "imageUrl": "https://frey.freyala.com/meta/list?items="
    },
    {
        "collectionName": "Harmoonies",
        "tokenName": "Harmoonie",
        "image": "https://api.harmoonies.one/thumbnails/2134",
        "status": "OPEN",
        "token": "0x8EA0b71eB3AF2f6Be08fF43D354D4215D0ab397a",
        "imageUrl": "https://api.harmoonies.one/thumbnails/"
    }
]